{
  "authorization_endpoint": "https://auth.octopus.energy/authorize/",
  "claims_supported": [
    "sub"
  ],
  "end_session_endpoint": "https://auth.octopus.energy/logout/",
  "id_token_signing_alg_values_supported": [
    "HS256",
    "RS256"
  ],
  "issuer": "https://auth.octopus.energy/token/",
  "jwks_uri": "https://auth.octopus.energy/.well-known/jwks.json",
  "response_types_supported": [
    "code",
    "token",
    "id_token",
    "id_token token",
    "code token",
    "code id_token",
    "code id_token token"
  ],
  "revocation_endpoint": "https://auth.octopus.energy/revoke-token/",
  "scopes_supported": [
    "openid",
    "full-customer-access",
    "update:account-details",
    "update:reading-consent-granularity",
    "query:mfa-device",
    "query:on-site-jobs-appointments",
    "query:portfolios",
    "cancel:siteworks-appointments",
    "accept:fit-terms-and-conditions",
    "report:move-out",
    "verify:customer-details",
    "query:goods-quotes",
    "view:account-user-permissions",
    "manage:contribution-agreements",
    "create:customer-feedback",
    "create:payment-method-action-intents",
    "redeem:loyalty-points",
    "update:ssd",
    "occupy:accounts",
    "create:payment-action-intents",
    "create:repayment-request",
    "view:customer-communications",
    "transfer:loyalty-points",
    "add:campaign-to-account",
    "query:payment-instructions",
    "request:consumption-data",
    "create:quoting-offer-group",
    "register:smartflex-devices",
    "view:octocare-usage-info",
    "query:billing-information",
    "create:goods-quotes",
    "create:centrepay-deductions",
    "change:centrepay-deductions",
    "query:payment-preferences",
    "create:on-site-jobs-requests",
    "update:dd-day",
    "initiate:standalone-payments",
    "accept:terms-and-conditions",
    "view:campaign-dashboards",
    "cancel:enrollment",
    "manage:ev",
    "view:detailed-usage",
    "view:api-key",
    "query:devices",
    "manage:payment-schedules",
    "edit:customer-marketing-preference",
    "submit:meter-readings",
    "manage:account-renewals",
    "cancel:centrepay-deductions",
    "manage:product-enrolment",
    "update:smart-meter-interest",
    "update:dd-amount",
    "review:quote",
    "submit:fit-meter-readings",
    "access:customer-queries",
    "update:user-details",
    "validate:mfa-device",
    "query:account-reminders",
    "query:user-details",
    "view:sensitive-customer-information",
    "query:customer-flexibility-campaigns",
    "view:customer-marketing-preference",
    "manage:goods-purchases",
    "query:agreements",
    "query:complaints",
    "query:personally-identifiable-information",
    "query:fit-installations",
    "process:move-outs",
    "query:auto-topup-config",
    "add:credit-to-smart-meter",
    "query:loyalty-points-ledger-entry",
    "create:complaints",
    "query:account-applications",
    "query:goods-products",
    "query:contribution-agreements",
    "book:smart-meter-appointments",
    "update:smart-meter-data-preferences",
    "update:sensitive-customer-information",
    "view:smartflex-data",
    "query:fit-schedules",
    "query:contracts",
    "send:loss-objection-for-change-of-supplier",
    "query:businesses",
    "query:account-payments",
    "create:on-site-jobs-appointments",
    "provide:missing-meter-point-details",
    "submit:customer-feedback",
    "checkout:quote",
    "query:property-meters",
    "query:loyalty-points-balance",
    "create:mfa-device",
    "view:account-number",
    "view:octocare-onboarding-info",
    "accept:fit-schedules",
    "manage:customer-assets",
    "configure:auto-topup-config",
    "query:workflows",
    "create:payment-instructions",
    "escalate:ink-conversation",
    "query:lifecycle-processes",
    "manage:ink-live-chat",
    "query:property",
    "query:on-site-jobs-requests",
    "join:campaigns",
    "set:loyalty-points-user",
    "query:authorized-applications",
    "cancel:on-site-jobs-appointments",
    "join:campaign-events",
    "view:ev-data",
    "amend:payments",
    "query:loyalty-enrollment-eligibility",
    "delete:mfa-device",
    "query:establishments",
    "query:customer-assets",
    "view:account-type",
    "create:property",
    "query:account-campaigns"
  ],
  "subject_types_supported": [
    "public"
  ],
  "token_endpoint": "https://auth.octopus.energy/token/",
  "token_endpoint_auth_methods_supported": [
    "client_secret_post",
    "client_secret_basic"
  ],
  "userinfo_endpoint": "https://auth.octopus.energy/userinfo/"
}